{"default_tenant_id":null,"policies":[],"predicates":[{"comparator":"equals","expected":"production","policy_tags":[],"predicate":"env_is_prod","query":{"params":{"key":"DEPLOY_ENV"},"predicate":"get","provider_id":"env"}},{"comparator":"equals","expected":true,"policy_tags":[],"predicate":"after_freeze","query":{"params":{"timestamp":1710000000000},"predicate":"after","provider_id":"time"}}],"scenario_id":"example-scenario","schemas":[],"spec_version":"v1","stages":[{"advance_to":{"kind":"terminal"},"entry_packets":[{"content_type":"application/json","expiry":null,"packet_id":"packet-hello","payload":{"kind":"json","value":{"message":"hello","purpose":"scenario entry packet"}},"policy_tags":[],"schema_id":"schema-hello","visibility_labels":["public"]}],"gates":[{"gate_id":"env_gate","requirement":{"Predicate":"env_is_prod"}},{"gate_id":"time_gate","requirement":{"Predicate":"after_freeze"}}],"on_timeout":"fail","stage_id":"main","timeout":null}]}